{
    "name": "Plantilla_col4",
    "protocol": "sftp",
    "host": "172.31.158.12",
    "username": "E10356",
    "password": "fate.2390",
    "port": 22,

    "remotePath": "/home/E10356/plantilla-web",
    "uploadOnSave": false,
    "downloadOnOpen": false,
    "ignore": [
        "*.log",
        "*.sql",
        "*.sqlite3",
        "media_root/",
        "static_root/",
        "__pycache__/",
        ".ipynb_checkpoints",
        "*.pid",
        "*raw/",
        "*sock/",
        "frontend",
        "bat-files",
        ".gitignore",
        "documentacion",
        ".vscode",
        "readme.md",
        "sftp-config.json",
        ".bat"
    ]

}